lbaf/__init__.py
lbaf/__main__.py
lbaf/Applications/LBAF_app.py
lbaf/Applications/MoveCountsViewer.py
lbaf/Applications/__init__.py
lbaf/Execution/__init__.py
lbaf/Execution/lbsAlgorithmBase.py
lbaf/Execution/lbsBruteForceAlgorithm.py
lbaf/Execution/lbsCentralizedPrefixOptimizerAlgorithm.py
lbaf/Execution/lbsClusteringTransferStrategy.py
lbaf/Execution/lbsCriterionBase.py
lbaf/Execution/lbsInformAndTransferAlgorithm.py
lbaf/Execution/lbsPhaseStepperAlgorithm.py
lbaf/Execution/lbsRecursiveTransferStrategy.py
lbaf/Execution/lbsRuntime.py
lbaf/Execution/lbsStrictLocalizingCriterion.py
lbaf/Execution/lbsTemperedCriterion.py
lbaf/Execution/lbsTransferStrategyBase.py
lbaf/IO/__init__.py
lbaf/IO/lbsConfigurationUpgrader.py
lbaf/IO/lbsConfigurationValidator.py
lbaf/IO/lbsGridStreamer.py
lbaf/IO/lbsStatistics.py
lbaf/IO/lbsVTDataReader.py
lbaf/IO/lbsVTDataWriter.py
lbaf/IO/lbsVisualizer.py
lbaf/Model/__init__.py
lbaf/Model/lbsAffineCombinationWorkModel.py
lbaf/Model/lbsBlock.py
lbaf/Model/lbsLoadOnlyWorkModel.py
lbaf/Model/lbsMessage.py
lbaf/Model/lbsObject.py
lbaf/Model/lbsObjectCommunicator.py
lbaf/Model/lbsPhase.py
lbaf/Model/lbsRank.py
lbaf/Model/lbsWorkModelBase.py
lbaf/Utils/__init__.py
lbaf/Utils/lbsArgumentParser.py
lbaf/Utils/lbsColors.py
lbaf/Utils/lbsCsv2JsonDataConverter.py
lbaf/Utils/lbsDataStatFilesUpdater.py
lbaf/Utils/lbsJSONDataFilesValidatorLoader.py
lbaf/Utils/lbsLogging.py
lbaf/Utils/lbsPath.py
lbaf/Utils/lbsVTDataExtractor.py
lbaf/Utils/lbsWeb.py
lbaf-1.0.1.dist-info/LICENSE
lbaf-1.0.1.dist-info/METADATA
lbaf-1.0.1.dist-info/WHEEL
lbaf-1.0.1.dist-info/entry_points.txt
lbaf-1.0.1.dist-info/top_level.txt
lbaf-1.0.1.dist-info/RECORD
